HolyGrail-0.2.1.Perceval.dist-info/metadata.json
HolyGrail-0.2.1.Perceval.dist-info/METADATA
HolyGrail-0.2.1.Perceval.dist-info/WHEEL
HolyGrail-0.2.1.Perceval.dist-info/RECORD
HolyGrail-0.2.1.Perceval.dist-info/top_level.txt
HolyGrail-0.2.1.Perceval.dist-info/DESCRIPTION.rst
holygrail/holygrail.py
holygrail/holygrail_exceptions.py
holygrail/test_holygrail.py
holygrail/__init__.py
