Metadata-Version: 2.0
Name: HolyGrail
Version: 0.2.1.Perceval
Summary: High level lib to manage the holy quests of your life (in other words GTD next actions)
Home-page: https://github.com/psycojoker/holygrail
Author: Laurent Peuch
Author-email: cortex@worlddomination.be
License: aGPLv3+
Keywords: gtd lib holygrail
Platform: UNKNOWN
Requires-Dist: sqlobject
